<restaurantConfig><name>D1f1rFxRux</name><location><city>Philadelphia</city><zipcode>85151</zipcode></location><currency>USD</currency><timezone>EST</timezone><menu><category><name>Chicken &amp; Sandwiches</name><item><name>Buttermilk Crispy Chicken Sandwich</name><price>8.18</price></item><item><name>McChicken Deluxe</name><price>4.41</price></item><item><name>Artisan Grilled Chicken Sandwich</name><price>9.27</price></item><item><name>Spicy McChicken</name><price>5.15</price></item></category><category><name>Salads</name><item><name>Bacon Ranch Salad</name><price>5.39</price></item></category><category><name>Snacks &amp; Sides</name><item><name>French Fries</name><price>6.37</price></item><item><name>Apple Slices</name><price>3.5</price></item><item><name>McNuggets</name><price>7.6</price></item></category></menu><employees><employee><name>0vaUUoM6</name><position>Cashier</position><hourlyWage>8.19</hourlyWage></employee><employee><name>OUEneQMj</name><position>Waiter</position><hourlyWage>19.75</hourlyWage></employee><employee><name>jv1Rqa4O</name><position>Manager</position><hourlyWage>17.34</hourlyWage></employee><employee><name>rULct0a8</name><position>Manager</position><hourlyWage>8.79</hourlyWage></employee><employee><name>Cbhr3ruk</name><position>Cashier</position><hourlyWage>18.98</hourlyWage></employee></employees><operatingHours><day><name>Monday</name><openingTime>09:00</openingTime><closingTime>22:00</closingTime></day><day><name>Tuesday</name><openingTime>09:00</openingTime><closingTime>22:00</closingTime></day><day><name>Wednesday</name><openingTime>09:00</openingTime><closingTime>22:00</closingTime></day><day><name>Thursday</name><openingTime>09:00</openingTime><closingTime>22:00</closingTime></day><day><name>Friday</name><openingTime>09:00</openingTime><closingTime>22:00</closingTime></day><day><name>Saturday</name><openingTime>09:00</openingTime><closingTime>22:00</closingTime></day><day><name>Sunday</name><openingTime>09:00</openingTime><closingTime>22:00</closingTime></day></operatingHours><onlineOrdering>true</onlineOrdering><loyaltyProgramEnabled>false</loyaltyProgramEnabled><driveThruAvailable>false</driveThruAvailable><language>German</language><taxReference>kzcxYL1m</taxReference><operations /></restaurantConfig>