<restaurantConfig><name>OBYmwCFQ7h</name><location><city>Tulsa</city><zipcode>12741</zipcode></location><currency>USD</currency><timezone>EST</timezone><menu><category><name>Chicken &amp; Sandwiches</name><item><name>Spicy McChicken</name><price>3.83</price></item><item><name>McChicken Deluxe</name><price>8.73</price></item><item><name>Artisan Grilled Chicken Sandwich</name><price>5.86</price></item><item><name>Buttermilk Crispy Chicken Sandwich</name><price>9.16</price></item></category><category><name>Breakfast</name><item><name>Egg McMuffin</name><price>7.34</price></item></category></menu><employees><employee><name>UxW5KfRb</name><position>Cashier</position><hourlyWage>9.99</hourlyWage></employee><employee><name>cRYPm9QH</name><position>Manager</position><hourlyWage>14.96</hourlyWage></employee><employee><name>YnjxuqSh</name><position>Cashier</position><hourlyWage>8.81</hourlyWage></employee><employee><name>VNNR45ux</name><position>Waiter</position><hourlyWage>14.13</hourlyWage></employee><employee><name>UpUe4tSt</name><position>Cashier</position><hourlyWage>14.09</hourlyWage></employee><employee><name>ISCqLQAC</name><position>Waiter</position><hourlyWage>16.66</hourlyWage></employee><employee><name>vfugvrDe</name><position>Cook</position><hourlyWage>10.52</hourlyWage></employee><employee><name>IzUfnAQI</name><position>Waiter</position><hourlyWage>10.49</hourlyWage></employee><employee><name>r9lgXbzq</name><position>Cashier</position><hourlyWage>15.66</hourlyWage></employee></employees><operatingHours><day><name>Monday</name><openingTime>09:00</openingTime><closingTime>22:00</closingTime></day><day><name>Tuesday</name><openingTime>09:00</openingTime><closingTime>22:00</closingTime></day><day><name>Wednesday</name><openingTime>09:00</openingTime><closingTime>22:00</closingTime></day><day><name>Thursday</name><openingTime>09:00</openingTime><closingTime>22:00</closingTime></day><day><name>Friday</name><openingTime>09:00</openingTime><closingTime>22:00</closingTime></day><day><name>Saturday</name><openingTime>09:00</openingTime><closingTime>22:00</closingTime></day><day><name>Sunday</name><openingTime>09:00</openingTime><closingTime>22:00</closingTime></day></operatingHours><onlineOrdering>false</onlineOrdering><loyaltyProgramEnabled>false</loyaltyProgramEnabled><driveThruAvailable>true</driveThruAvailable><language>Spanish</language><taxReference>mNc96v6R</taxReference><operations /></restaurantConfig>