<restaurantConfig><name>pWoxy3rMIP</name><location><city>Arlington</city><zipcode>51449</zipcode></location><currency>USD</currency><timezone>EST</timezone><menu><category><name>Burgers</name><item><name>Big Mac</name><price>8.9</price></item></category><category><name>Salads</name><item><name>Southwest Grilled Chicken Salad</name><price>5.2</price></item></category><category><name>Breakfast</name><item><name>Sausage McMuffin</name><price>1.84</price></item><item><name>Big Breakfast</name><price>2.9</price></item><item><name>Hotcakes</name><price>1.35</price></item></category><category><name>Snacks &amp; Sides</name><item><name>McNuggets</name><price>6.98</price></item><item><name>French Fries</name><price>7.59</price></item><item><name>Apple Slices</name><price>6.57</price></item></category></menu><employees><employee><name>QJil2NZq</name><position>Cashier</position><hourlyWage>16.06</hourlyWage></employee></employees><operatingHours><day><name>Monday</name><openingTime>09:00</openingTime><closingTime>22:00</closingTime></day><day><name>Tuesday</name><openingTime>09:00</openingTime><closingTime>22:00</closingTime></day><day><name>Wednesday</name><openingTime>09:00</openingTime><closingTime>22:00</closingTime></day><day><name>Thursday</name><openingTime>09:00</openingTime><closingTime>22:00</closingTime></day><day><name>Friday</name><openingTime>09:00</openingTime><closingTime>22:00</closingTime></day><day><name>Saturday</name><openingTime>09:00</openingTime><closingTime>22:00</closingTime></day><day><name>Sunday</name><openingTime>09:00</openingTime><closingTime>22:00</closingTime></day></operatingHours><onlineOrdering>false</onlineOrdering><loyaltyProgramEnabled>false</loyaltyProgramEnabled><driveThruAvailable>true</driveThruAvailable><language>French</language><taxReference>Pg7pdzDo</taxReference><operations /></restaurantConfig>