<restaurantConfig><name>lWBRrgfHM9</name><location><city>Long Beach</city><zipcode>99141</zipcode></location><currency>USD</currency><timezone>EST</timezone><menu><category><name>Breakfast</name><item><name>Hotcakes</name><price>6.7</price></item><item><name>Sausage McMuffin</name><price>7.55</price></item><item><name>Big Breakfast</name><price>1.03</price></item><item><name>Egg McMuffin</name><price>8.4</price></item><item><name>Hash Browns</name><price>3.26</price></item></category></menu><employees><employee><name>qClzOCGe</name><position>Waiter</position><hourlyWage>16.0</hourlyWage></employee><employee><name>eY5Litva</name><position>Cashier</position><hourlyWage>17.85</hourlyWage></employee></employees><operatingHours><day><name>Monday</name><openingTime>09:00</openingTime><closingTime>22:00</closingTime></day><day><name>Tuesday</name><openingTime>09:00</openingTime><closingTime>22:00</closingTime></day><day><name>Wednesday</name><openingTime>09:00</openingTime><closingTime>22:00</closingTime></day><day><name>Thursday</name><openingTime>09:00</openingTime><closingTime>22:00</closingTime></day><day><name>Friday</name><openingTime>09:00</openingTime><closingTime>22:00</closingTime></day><day><name>Saturday</name><openingTime>09:00</openingTime><closingTime>22:00</closingTime></day><day><name>Sunday</name><openingTime>09:00</openingTime><closingTime>22:00</closingTime></day></operatingHours><onlineOrdering>false</onlineOrdering><loyaltyProgramEnabled>false</loyaltyProgramEnabled><driveThruAvailable>true</driveThruAvailable><language>English</language><taxReference>fsBo8Lx6</taxReference><operations /></restaurantConfig>