<restaurantConfig><name>74s1LHjpEw</name><location><city>Mesa</city><zipcode>49616</zipcode></location><currency>USD</currency><timezone>EST</timezone><menu><category><name>Burgers</name><item><name>Big Mac</name><price>9.83</price></item><item><name>McChicken</name><price>8.91</price></item><item><name>McDouble</name><price>8.94</price></item></category><category><name>Chicken &amp; Sandwiches</name><item><name>Spicy McChicken</name><price>2.97</price></item><item><name>McChicken Deluxe</name><price>3.31</price></item><item><name>Artisan Grilled Chicken Sandwich</name><price>4.46</price></item></category><category><name>Salads</name><item><name>Bacon Ranch Salad</name><price>7.52</price></item></category></menu><employees><employee><name>Ux6jTYNw</name><position>Cashier</position><hourlyWage>9.32</hourlyWage></employee><employee><name>Kl5M0BOH</name><position>Manager</position><hourlyWage>19.68</hourlyWage></employee><employee><name>lAWwnapq</name><position>Manager</position><hourlyWage>10.32</hourlyWage></employee><employee><name>MMwNX0Jx</name><position>Manager</position><hourlyWage>17.7</hourlyWage></employee><employee><name>Xw0yFeXT</name><position>Manager</position><hourlyWage>18.02</hourlyWage></employee><employee><name>MY0CeA1P</name><position>Cashier</position><hourlyWage>9.76</hourlyWage></employee><employee><name>0pKwGSOc</name><position>Manager</position><hourlyWage>9.02</hourlyWage></employee><employee><name>mW9l9OKy</name><position>Cook</position><hourlyWage>15.67</hourlyWage></employee><employee><name>oxfFNyhc</name><position>Cook</position><hourlyWage>12.47</hourlyWage></employee></employees><operatingHours><day><name>Monday</name><openingTime>09:00</openingTime><closingTime>22:00</closingTime></day><day><name>Tuesday</name><openingTime>09:00</openingTime><closingTime>22:00</closingTime></day><day><name>Wednesday</name><openingTime>09:00</openingTime><closingTime>22:00</closingTime></day><day><name>Thursday</name><openingTime>09:00</openingTime><closingTime>22:00</closingTime></day><day><name>Friday</name><openingTime>09:00</openingTime><closingTime>22:00</closingTime></day><day><name>Saturday</name><openingTime>09:00</openingTime><closingTime>22:00</closingTime></day><day><name>Sunday</name><openingTime>09:00</openingTime><closingTime>22:00</closingTime></day></operatingHours><onlineOrdering>true</onlineOrdering><loyaltyProgramEnabled>true</loyaltyProgramEnabled><driveThruAvailable>false</driveThruAvailable><language>Spanish</language><taxReference>n7vHugTn</taxReference><operations /></restaurantConfig>