<restaurantConfig><name>2NDKWA4jCj</name><location><city>San Francisco</city><zipcode>62766</zipcode></location><currency>USD</currency><timezone>EST</timezone><menu><category><name>Breakfast</name><item><name>Egg McMuffin</name><price>8.91</price></item><item><name>Hash Browns</name><price>9.33</price></item><item><name>Sausage McMuffin</name><price>2.23</price></item><item><name>Big Breakfast</name><price>6.17</price></item><item><name>Hotcakes</name><price>8.56</price></item></category></menu><employees><employee><name>FEH0Munv</name><position>Cook</position><hourlyWage>18.86</hourlyWage></employee><employee><name>KBCDbA03</name><position>Cook</position><hourlyWage>10.76</hourlyWage></employee><employee><name>CFp2y6aL</name><position>Cook</position><hourlyWage>8.18</hourlyWage></employee><employee><name>JqFyoHJ8</name><position>Cashier</position><hourlyWage>12.82</hourlyWage></employee><employee><name>v7XHY24V</name><position>Cook</position><hourlyWage>19.27</hourlyWage></employee></employees><operatingHours><day><name>Monday</name><openingTime>09:00</openingTime><closingTime>22:00</closingTime></day><day><name>Tuesday</name><openingTime>09:00</openingTime><closingTime>22:00</closingTime></day><day><name>Wednesday</name><openingTime>09:00</openingTime><closingTime>22:00</closingTime></day><day><name>Thursday</name><openingTime>09:00</openingTime><closingTime>22:00</closingTime></day><day><name>Friday</name><openingTime>09:00</openingTime><closingTime>22:00</closingTime></day><day><name>Saturday</name><openingTime>09:00</openingTime><closingTime>22:00</closingTime></day><day><name>Sunday</name><openingTime>09:00</openingTime><closingTime>22:00</closingTime></day></operatingHours><onlineOrdering>true</onlineOrdering><loyaltyProgramEnabled>true</loyaltyProgramEnabled><driveThruAvailable>false</driveThruAvailable><language>French</language><taxReference>enjhiibm</taxReference><operations /></restaurantConfig>