<restaurantConfig><name>rBg3yidGLt</name><location><city>San Jose</city><zipcode>83305</zipcode></location><currency>USD</currency><timezone>EST</timezone><menu><category><name>Salads</name><item><name>Southwest Grilled Chicken Salad</name><price>1.46</price></item><item><name>Side Salad</name><price>1.57</price></item></category><category><name>Breakfast</name><item><name>Egg McMuffin</name><price>6.52</price></item><item><name>Hotcakes</name><price>1.67</price></item><item><name>Big Breakfast</name><price>1.99</price></item></category></menu><employees><employee><name>lrFwda7Z</name><position>Waiter</position><hourlyWage>18.38</hourlyWage></employee><employee><name>u57gUxnH</name><position>Waiter</position><hourlyWage>17.52</hourlyWage></employee><employee><name>TMUbGubY</name><position>Waiter</position><hourlyWage>15.4</hourlyWage></employee></employees><operatingHours><day><name>Monday</name><openingTime>09:00</openingTime><closingTime>22:00</closingTime></day><day><name>Tuesday</name><openingTime>09:00</openingTime><closingTime>22:00</closingTime></day><day><name>Wednesday</name><openingTime>09:00</openingTime><closingTime>22:00</closingTime></day><day><name>Thursday</name><openingTime>09:00</openingTime><closingTime>22:00</closingTime></day><day><name>Friday</name><openingTime>09:00</openingTime><closingTime>22:00</closingTime></day><day><name>Saturday</name><openingTime>09:00</openingTime><closingTime>22:00</closingTime></day><day><name>Sunday</name><openingTime>09:00</openingTime><closingTime>22:00</closingTime></day></operatingHours><onlineOrdering>true</onlineOrdering><loyaltyProgramEnabled>false</loyaltyProgramEnabled><driveThruAvailable>true</driveThruAvailable><language>Spanish</language><taxReference>Eohuk9aA</taxReference><operations /></restaurantConfig>