<restaurantConfig><name>K8Up2KxpBe</name><location><city>Indianapolis</city><zipcode>20175</zipcode></location><currency>USD</currency><timezone>EST</timezone><menu><category><name>Burgers</name><item><name>McChicken</name><price>7.96</price></item></category><category><name>Breakfast</name><item><name>Hotcakes</name><price>3.78</price></item><item><name>Egg McMuffin</name><price>4.52</price></item><item><name>Sausage McMuffin</name><price>4.78</price></item><item><name>Big Breakfast</name><price>5.44</price></item><item><name>Hash Browns</name><price>6.81</price></item></category></menu><employees><employee><name>5sUK4DXe</name><position>Cashier</position><hourlyWage>17.16</hourlyWage></employee></employees><operatingHours><day><name>Monday</name><openingTime>09:00</openingTime><closingTime>22:00</closingTime></day><day><name>Tuesday</name><openingTime>09:00</openingTime><closingTime>22:00</closingTime></day><day><name>Wednesday</name><openingTime>09:00</openingTime><closingTime>22:00</closingTime></day><day><name>Thursday</name><openingTime>09:00</openingTime><closingTime>22:00</closingTime></day><day><name>Friday</name><openingTime>09:00</openingTime><closingTime>22:00</closingTime></day><day><name>Saturday</name><openingTime>09:00</openingTime><closingTime>22:00</closingTime></day><day><name>Sunday</name><openingTime>09:00</openingTime><closingTime>22:00</closingTime></day></operatingHours><onlineOrdering>true</onlineOrdering><loyaltyProgramEnabled>false</loyaltyProgramEnabled><driveThruAvailable>true</driveThruAvailable><language>German</language><taxReference>VZ1Bww9w</taxReference><operations /></restaurantConfig>