<restaurantConfig><name>7M1odqkPBj</name><location><city>Fort Worth</city><zipcode>95698</zipcode></location><currency>USD</currency><timezone>EST</timezone><menu><category><name>Burgers</name><item><name>Filet-O-Fish</name><price>2.58</price></item></category><category><name>Salads</name><item><name>Southwest Grilled Chicken Salad</name><price>8.95</price></item><item><name>Bacon Ranch Salad</name><price>3.83</price></item><item><name>Side Salad</name><price>9.56</price></item></category></menu><employees><employee><name>ftMvHlev</name><position>Manager</position><hourlyWage>12.57</hourlyWage></employee><employee><name>CQ9OLTzP</name><position>Cook</position><hourlyWage>16.14</hourlyWage></employee><employee><name>1EOGcb0d</name><position>Cashier</position><hourlyWage>19.27</hourlyWage></employee><employee><name>cq0OdVDx</name><position>Cashier</position><hourlyWage>19.81</hourlyWage></employee><employee><name>feGarIw8</name><position>Manager</position><hourlyWage>13.11</hourlyWage></employee><employee><name>h8bwEGN2</name><position>Manager</position><hourlyWage>9.54</hourlyWage></employee></employees><operatingHours><day><name>Monday</name><openingTime>09:00</openingTime><closingTime>22:00</closingTime></day><day><name>Tuesday</name><openingTime>09:00</openingTime><closingTime>22:00</closingTime></day><day><name>Wednesday</name><openingTime>09:00</openingTime><closingTime>22:00</closingTime></day><day><name>Thursday</name><openingTime>09:00</openingTime><closingTime>22:00</closingTime></day><day><name>Friday</name><openingTime>09:00</openingTime><closingTime>22:00</closingTime></day><day><name>Saturday</name><openingTime>09:00</openingTime><closingTime>22:00</closingTime></day><day><name>Sunday</name><openingTime>09:00</openingTime><closingTime>22:00</closingTime></day></operatingHours><onlineOrdering>false</onlineOrdering><loyaltyProgramEnabled>false</loyaltyProgramEnabled><driveThruAvailable>true</driveThruAvailable><language>English</language><taxReference>JdAK65Ek</taxReference><operations /></restaurantConfig>