<restaurantConfig><name>EN7pA4QpDN</name><location><city>Chicago</city><zipcode>57777</zipcode></location><currency>USD</currency><timezone>EST</timezone><menu><category><name>Burgers</name><item><name>Quarter Pounder with Cheese</name><price>6.15</price></item><item><name>Filet-O-Fish</name><price>3.52</price></item><item><name>McDouble</name><price>5.42</price></item><item><name>Big Mac</name><price>9.22</price></item></category><category><name>Salads</name><item><name>Southwest Grilled Chicken Salad</name><price>9.8</price></item><item><name>Side Salad</name><price>2.95</price></item><item><name>Bacon Ranch Salad</name><price>4.89</price></item></category><category><name>Breakfast</name><item><name>Hotcakes</name><price>7.43</price></item><item><name>Hash Browns</name><price>1.8</price></item><item><name>Sausage McMuffin</name><price>5.12</price></item></category><category><name>Snacks &amp; Sides</name><item><name>McNuggets</name><price>7.76</price></item></category></menu><employees><employee><name>daQU4QCx</name><position>Cook</position><hourlyWage>18.85</hourlyWage></employee><employee><name>JEaE8QZE</name><position>Manager</position><hourlyWage>17.16</hourlyWage></employee><employee><name>qWB8RFZT</name><position>Cook</position><hourlyWage>16.21</hourlyWage></employee><employee><name>i7tSOyys</name><position>Manager</position><hourlyWage>13.67</hourlyWage></employee><employee><name>wWaZ7eAw</name><position>Waiter</position><hourlyWage>8.55</hourlyWage></employee></employees><operatingHours><day><name>Monday</name><openingTime>09:00</openingTime><closingTime>22:00</closingTime></day><day><name>Tuesday</name><openingTime>09:00</openingTime><closingTime>22:00</closingTime></day><day><name>Wednesday</name><openingTime>09:00</openingTime><closingTime>22:00</closingTime></day><day><name>Thursday</name><openingTime>09:00</openingTime><closingTime>22:00</closingTime></day><day><name>Friday</name><openingTime>09:00</openingTime><closingTime>22:00</closingTime></day><day><name>Saturday</name><openingTime>09:00</openingTime><closingTime>22:00</closingTime></day><day><name>Sunday</name><openingTime>09:00</openingTime><closingTime>22:00</closingTime></day></operatingHours><onlineOrdering>false</onlineOrdering><loyaltyProgramEnabled>false</loyaltyProgramEnabled><driveThruAvailable>true</driveThruAvailable><language>Spanish</language><taxReference>Hs1XwQTM</taxReference><operations /></restaurantConfig>